<annotation>
	<folder>Folder</folder>
	<filename>2008_000640.jpg</filename>
	<path>/home/marqueza/Downloads/labelImg-master/Folder/2008_000640.jpg</path>
	<source>
		<database>Unknown</database>
	</source>
	<size>
		<width>320</width>
		<height>240</height>
		<depth>3</depth>
	</size>
	<segmented>0</segmented>
	<object>
		<name>without_mask</name>
		<pose>Unspecified</pose>
		<truncated>0</truncated>
		<difficult>0</difficult>
		<bndbox>
			<xmin>128</xmin>
			<ymin>30</ymin>
			<xmax>200</xmax>
			<ymax>114</ymax>
		</bndbox>
	</object>
	<object>
		<name>without_mask</name>
		<pose>Unspecified</pose>
		<truncated>0</truncated>
		<difficult>0</difficult>
		<bndbox>
			<xmin>135</xmin>
			<ymin>142</ymin>
			<xmax>198</xmax>
			<ymax>208</ymax>
		</bndbox>
	</object>
</annotation>
