<annotation>
	<folder>Folder</folder>
	<filename>2008_001039.jpg</filename>
	<path>/home/marqueza/Downloads/labelImg-master/Folder/2008_001039.jpg</path>
	<source>
		<database>Unknown</database>
	</source>
	<size>
		<width>500</width>
		<height>324</height>
		<depth>3</depth>
	</size>
	<segmented>0</segmented>
	<object>
		<name>without_mask</name>
		<pose>Unspecified</pose>
		<truncated>0</truncated>
		<difficult>0</difficult>
		<bndbox>
			<xmin>346</xmin>
			<ymin>146</ymin>
			<xmax>371</xmax>
			<ymax>175</ymax>
		</bndbox>
	</object>
	<object>
		<name>without_mask</name>
		<pose>Unspecified</pose>
		<truncated>0</truncated>
		<difficult>0</difficult>
		<bndbox>
			<xmin>271</xmin>
			<ymin>145</ymin>
			<xmax>282</xmax>
			<ymax>157</ymax>
		</bndbox>
	</object>
	<object>
		<name>without_mask</name>
		<pose>Unspecified</pose>
		<truncated>0</truncated>
		<difficult>0</difficult>
		<bndbox>
			<xmin>180</xmin>
			<ymin>164</ymin>
			<xmax>193</xmax>
			<ymax>176</ymax>
		</bndbox>
	</object>
</annotation>
