<annotation>
	<folder>Folder</folder>
	<filename>2008_001329.jpg</filename>
	<path>/home/marqueza/Downloads/labelImg-master/Folder/2008_001329.jpg</path>
	<source>
		<database>Unknown</database>
	</source>
	<size>
		<width>375</width>
		<height>500</height>
		<depth>3</depth>
	</size>
	<segmented>0</segmented>
	<object>
		<name>without_mask</name>
		<pose>Unspecified</pose>
		<truncated>0</truncated>
		<difficult>0</difficult>
		<bndbox>
			<xmin>128</xmin>
			<ymin>188</ymin>
			<xmax>146</xmax>
			<ymax>207</ymax>
		</bndbox>
	</object>
	<object>
		<name>without_mask</name>
		<pose>Unspecified</pose>
		<truncated>0</truncated>
		<difficult>0</difficult>
		<bndbox>
			<xmin>111</xmin>
			<ymin>182</ymin>
			<xmax>124</xmax>
			<ymax>193</ymax>
		</bndbox>
	</object>
	<object>
		<name>without_mask</name>
		<pose>Unspecified</pose>
		<truncated>0</truncated>
		<difficult>0</difficult>
		<bndbox>
			<xmin>69</xmin>
			<ymin>190</ymin>
			<xmax>83</xmax>
			<ymax>204</ymax>
		</bndbox>
	</object>
	<object>
		<name>without_mask</name>
		<pose>Unspecified</pose>
		<truncated>0</truncated>
		<difficult>0</difficult>
		<bndbox>
			<xmin>90</xmin>
			<ymin>211</ymin>
			<xmax>101</xmax>
			<ymax>222</ymax>
		</bndbox>
	</object>
	<object>
		<name>without_mask</name>
		<pose>Unspecified</pose>
		<truncated>0</truncated>
		<difficult>0</difficult>
		<bndbox>
			<xmin>43</xmin>
			<ymin>183</ymin>
			<xmax>56</xmax>
			<ymax>194</ymax>
		</bndbox>
	</object>
</annotation>
