<annotation>
	<folder>Folder chinitos</folder>
	<filename>2020_02_47.jpg</filename>
	<path>/home/marqueza/Downloads/labelImg-master/Folder chinitos/2020_02_47.jpg</path>
	<source>
		<database>Unknown</database>
	</source>
	<size>
		<width>289</width>
		<height>455</height>
		<depth>3</depth>
	</size>
	<segmented>0</segmented>
	<object>
		<name>with_mask</name>
		<pose>Unspecified</pose>
		<truncated>1</truncated>
		<difficult>0</difficult>
		<bndbox>
			<xmin>2</xmin>
			<ymin>29</ymin>
			<xmax>289</xmax>
			<ymax>440</ymax>
		</bndbox>
	</object>
</annotation>
